napari_convpaint/__init__.py
napari_convpaint/_version.py
napari_convpaint/conv_paint_cellpose.py
napari_convpaint/conv_paint_combo_fe.py
napari_convpaint/conv_paint_dino.py
napari_convpaint/conv_paint_dino_jafar.py
napari_convpaint/conv_paint_fe_template.py
napari_convpaint/conv_paint_feature_extractor.py
napari_convpaint/conv_paint_gaussian.py
napari_convpaint/conv_paint_ilastik.py
napari_convpaint/conv_paint_model.py
napari_convpaint/conv_paint_nnlayers.py
napari_convpaint/conv_paint_param.py
napari_convpaint/conv_paint_utils.py
napari_convpaint/conv_paint_widget.py
napari_convpaint/convpaint_sample.py
napari_convpaint/napari.yml
napari_convpaint/utils.py
napari_convpaint/_tests/__init__.py
napari_convpaint/_tests/test_conv_paint.py
napari_convpaint/_tests/test_conv_paint_utils.py
napari_convpaint/_tests/test_dims.py
napari_convpaint/_tests/_tests/test_imgs/0000_ground_truth.png
napari_convpaint/_tests/_tests/test_imgs/0000_img.png
napari_convpaint/_tests/_tests/test_imgs/0000_scribbles_all_01500_w3.png
napari_convpaint/jafar/LICENSE.txt
napari_convpaint/jafar/checkpoints/info_checkpoints.md
napari_convpaint/jafar/layers/__init__.py
napari_convpaint/jafar/layers/attentions.py
napari_convpaint/jafar/layers/convolutions.py
napari_convpaint/jafar/layers/jafar.py
napari_convpaint/jafar/layers/other.py
napari_convpaint/jafar/layers/positional_encoding.py
napari_convpaint/jafar/layers/vit_wrapper.py
napari_convpaint-0.9.0.dist-info/licenses/LICENSE
napari_convpaint-0.9.0.dist-info/METADATA
napari_convpaint-0.9.0.dist-info/WHEEL
napari_convpaint-0.9.0.dist-info/entry_points.txt
napari_convpaint-0.9.0.dist-info/top_level.txt
napari_convpaint-0.9.0.dist-info/RECORD
