Metadata-Version: 2.4
Name: napari-convpaint
Version: 0.9.0
Summary: A plugin for segmentation by pixel classification using pre-trained neural networks for feature extraction
Home-page: https://github.com/guiwitz/napari-convpaint
Author: Guillaume Witz
Author-email: guillaume.witz@unibe.ch
License: BSD-3-Clause
Project-URL: Bug Tracker, https://github.com/guiwitz/napari-convpaint/issues
Project-URL: Documentation, https://github.com/guiwitz/napari-convpaint#README.md
Project-URL: Source Code, https://github.com/guiwitz/napari-convpaint
Project-URL: User Support, https://github.com/guiwitz/napari-convpaint/issues
Keywords: napari,plugin,segmentation,machine learning,deep learning,image analysis,neural networks
Classifier: Development Status :: 3 - Alpha
Classifier: Intended Audience :: Developers
Classifier: Intended Audience :: Science/Research
Classifier: Framework :: napari
Classifier: Topic :: Software Development :: Testing
Classifier: Topic :: Scientific/Engineering :: Image Recognition
Classifier: Topic :: Scientific/Engineering :: Artificial Intelligence
Classifier: Programming Language :: Python
Classifier: Programming Language :: Python :: 3
Classifier: Programming Language :: Python :: 3.10
Classifier: Programming Language :: Python :: 3.11
Classifier: Programming Language :: Python :: 3.12
Classifier: Operating System :: OS Independent
Classifier: License :: OSI Approved :: BSD License
Requires-Python: >=3.10
License-File: LICENSE
Requires-Dist: catboost>=1.2.8
Requires-Dist: dask
Requires-Dist: einops
Requires-Dist: joblib
Requires-Dist: magicgui
Requires-Dist: napari
Requires-Dist: napari-annotation-project
Requires-Dist: napari-guitils
Requires-Dist: numpy
Requires-Dist: omegaconf
Requires-Dist: pyyaml
Requires-Dist: qtpy
Requires-Dist: scikit-learn
Requires-Dist: scikit-image
Requires-Dist: tifffile
Requires-Dist: timm
Requires-Dist: torch<2.9.0
Requires-Dist: torchvision>=0.13.0
Requires-Dist: zarr
Provides-Extra: testing
Requires-Dist: tox; extra == "testing"
Requires-Dist: pytest; extra == "testing"
Requires-Dist: pytest-cov; extra == "testing"
Requires-Dist: pytest-qt; extra == "testing"
Requires-Dist: pyqt5; extra == "testing"
Provides-Extra: cellpose
Requires-Dist: cellpose<4; extra == "cellpose"
Provides-Extra: ilastik
Requires-Dist: ilastik-napari; extra == "ilastik"
Provides-Extra: qt
Requires-Dist: pyqt5; extra == "qt"
Dynamic: license-file
